<ArrayOfTeamGame xmlns:i="http://www.w3.org/2001/XMLSchema-instance"><TeamGame><StatID>174548</StatID><TeamID>5</TeamID><SeasonType>1</SeasonType><Season>2015</Season><Name>Orlando Magic</Name><Team>ORL</Team><Wins>0</Wins><Losses>1</Losses><GameID>57</GameID><OpponentID>23</OpponentID><Opponent>NO</Opponent><Day>10/28/2014</Day><DateTime>10/28/2014 8:00:00 PM</DateTime><HomeOrAway>AWAY</HomeOrAway><IsGameOver>True</IsGameOver><Updated>11/2/2015 11:55:33 PM</Updated><Games>1</Games><FantasyPoints>181.50</FantasyPoints><Minutes>237</Minutes><FieldGoalsMade>30</FieldGoalsMade><FieldGoalsAttempted>82</FieldGoalsAttempted><FieldGoalsPercentage>36.6</FieldGoalsPercentage><EffectiveFieldGoalsPercentage>39.0</EffectiveFieldGoalsPercentage><TwoPointersMade>26</TwoPointersMade><TwoPointersAttempted>71</TwoPointersAttempted><TwoPointersPercentage>36.6</TwoPointersPercentage><ThreePointersMade>4</ThreePointersMade><ThreePointersAttempted>11</ThreePointersAttempted><ThreePointersPercentage>36.4</ThreePointersPercentage><FreeThrowsMade>16</FreeThrowsMade><FreeThrowsAttempted>19</FreeThrowsAttempted><FreeThrowsPercentage>84.2</FreeThrowsPercentage><OffensiveRebounds>16</OffensiveRebounds><DefensiveRebounds>39</DefensiveRebounds><Rebounds>55</Rebounds><OffensiveReboundsPercentage i:nil="true"/><DefensiveReboundsPercentage i:nil="true"/><TotalReboundsPercentage i:nil="true"/><Assists>17</Assists><Steals>5</Steals><BlockedShots>9</BlockedShots><Turnovers>18</Turnovers><PersonalFouls>24</PersonalFouls><Points>80</Points><TrueShootingAttempts>90.36</TrueShootingAttempts><TrueShootingPercentage>44.2</TrueShootingPercentage><PlayerEfficiencyRating i:nil="true"/><AssistsPercentage i:nil="true"/><StealsPercentage i:nil="true"/><BlocksPercentage i:nil="true"/><TurnOversPercentage i:nil="true"/><UsageRatePercentage i:nil="true"/><FantasyPointsFanDuel>181.50</FantasyPointsFanDuel><FantasyPointsDraftKings>196.75</FantasyPointsDraftKings><FantasyPointsYahoo>183.50</FantasyPointsYahoo></TeamGame><TeamGame><StatID>174549</StatID><TeamID>23</TeamID><SeasonType>1</SeasonType><Season>2015</Season><Name>New Orleans Pelicans</Name><Team>NO</Team><Wins>1</Wins><Losses>0</Losses><GameID>57</GameID><OpponentID>5</OpponentID><Opponent>ORL</Opponent><Day>10/28/2014</Day><DateTime>10/28/2014 8:00:00 PM</DateTime><HomeOrAway>HOME</HomeOrAway><IsGameOver>True</IsGameOver><Updated>11/2/2015 11:55:33 PM</Updated><Games>1</Games><FantasyPoints>250.40</FantasyPoints><Minutes>240</Minutes><FieldGoalsMade>41</FieldGoalsMade><FieldGoalsAttempted>101</FieldGoalsAttempted><FieldGoalsPercentage>40.6</FieldGoalsPercentage><EffectiveFieldGoalsPercentage>42.6</EffectiveFieldGoalsPercentage><TwoPointersMade>37</TwoPointersMade><TwoPointersAttempted>84</TwoPointersAttempted><TwoPointersPercentage>44.0</TwoPointersPercentage><ThreePointersMade>4</ThreePointersMade><ThreePointersAttempted>17</ThreePointersAttempted><ThreePointersPercentage>23.5</ThreePointersPercentage><FreeThrowsMade>15</FreeThrowsMade><FreeThrowsAttempted>31</FreeThrowsAttempted><FreeThrowsPercentage>48.4</FreeThrowsPercentage><OffensiveRebounds>26</OffensiveRebounds><DefensiveRebounds>36</DefensiveRebounds><Rebounds>62</Rebounds><OffensiveReboundsPercentage i:nil="true"/><DefensiveReboundsPercentage i:nil="true"/><TotalReboundsPercentage i:nil="true"/><Assists>20</Assists><Steals>10</Steals><BlockedShots>17</BlockedShots><Turnovers>9</Turnovers><PersonalFouls>17</PersonalFouls><Points>101</Points><TrueShootingAttempts>114.64</TrueShootingAttempts><TrueShootingPercentage>44.1</TrueShootingPercentage><PlayerEfficiencyRating i:nil="true"/><AssistsPercentage i:nil="true"/><StealsPercentage i:nil="true"/><BlocksPercentage i:nil="true"/><TurnOversPercentage i:nil="true"/><UsageRatePercentage i:nil="true"/><FantasyPointsFanDuel>250.40</FantasyPointsFanDuel><FantasyPointsDraftKings>263.00</FantasyPointsDraftKings><FantasyPointsYahoo>252.40</FantasyPointsYahoo></TeamGame><TeamGame><StatID>174550</StatID><TeamID>24</TeamID><SeasonType>1</SeasonType><Season>2015</Season><Name>San Antonio Spurs</Name><Team>SA</Team><Wins>1</Wins><Losses>0</Losses><GameID>58</GameID><OpponentID>25</OpponentID><Opponent>DAL</Opponent><Day>10/28/2014</Day><DateTime>10/28/2014 8:00:00 PM</DateTime><HomeOrAway>HOME</HomeOrAway><IsGameOver>True</IsGameOver><Updated>11/2/2015 11:55:33 PM</Updated><Games>1</Games><FantasyPoints>177.10</FantasyPoints><Minutes>240</Minutes><FieldGoalsMade>37</FieldGoalsMade><FieldGoalsAttempted>70</FieldGoalsAttempted><FieldGoalsPercentage>52.9</FieldGoalsPercentage><EffectiveFieldGoalsPercentage>62.9</EffectiveFieldGoalsPercentage><TwoPointersMade>23</TwoPointersMade><TwoPointersAttempted>42</TwoPointersAttempted><TwoPointersPercentage>54.8</TwoPointersPercentage><ThreePointersMade>14</ThreePointersMade><ThreePointersAttempted>28</ThreePointersAttempted><ThreePointersPercentage>50.0</ThreePointersPercentage><FreeThrowsMade>13</FreeThrowsMade><FreeThrowsAttempted>16</FreeThrowsAttempted><FreeThrowsPercentage>81.2</FreeThrowsPercentage><OffensiveRebounds>9</OffensiveRebounds><DefensiveRebounds>29</DefensiveRebounds><Rebounds>38</Rebounds><OffensiveReboundsPercentage i:nil="true"/><DefensiveReboundsPercentage i:nil="true"/><TotalReboundsPercentage i:nil="true"/><Assists>23</Assists><Steals>5</Steals><BlockedShots>3</BlockedShots><Turnovers>20</Turnovers><PersonalFouls>20</PersonalFouls><Points>101</Points><TrueShootingAttempts>77.04</TrueShootingAttempts><TrueShootingPercentage>65.6</TrueShootingPercentage><PlayerEfficiencyRating i:nil="true"/><AssistsPercentage i:nil="true"/><StealsPercentage i:nil="true"/><BlocksPercentage i:nil="true"/><TurnOversPercentage i:nil="true"/><UsageRatePercentage i:nil="true"/><FantasyPointsFanDuel>177.10</FantasyPointsFanDuel><FantasyPointsDraftKings>197.50</FantasyPointsDraftKings><FantasyPointsYahoo>184.10</FantasyPointsYahoo></TeamGame><TeamGame><StatID>174551</StatID><TeamID>25</TeamID><SeasonType>1</SeasonType><Season>2015</Season><Name>Dallas Mavericks</Name><Team>DAL</Team><Wins>0</Wins><Losses>1</Losses><GameID>58</GameID><OpponentID>24</OpponentID><Opponent>SA</Opponent><Day>10/28/2014</Day><DateTime>10/28/2014 8:00:00 PM</DateTime><HomeOrAway>AWAY</HomeOrAway><IsGameOver>True</IsGameOver><Updated>11/2/2015 11:55:33 PM</Updated><Games>1</Games><FantasyPoints>179.10</FantasyPoints><Minutes>240</Minutes><FieldGoalsMade>38</FieldGoalsMade><FieldGoalsAttempted>78</FieldGoalsAttempted><FieldGoalsPercentage>48.7</FieldGoalsPercentage><EffectiveFieldGoalsPercentage>53.8</EffectiveFieldGoalsPercentage><TwoPointersMade>30</TwoPointersMade><TwoPointersAttempted>57</TwoPointersAttempted><TwoPointersPercentage>52.6</TwoPointersPercentage><ThreePointersMade>8</ThreePointersMade><ThreePointersAttempted>21</ThreePointersAttempted><ThreePointersPercentage>38.1</ThreePointersPercentage><FreeThrowsMade>16</FreeThrowsMade><FreeThrowsAttempted>19</FreeThrowsAttempted><FreeThrowsPercentage>84.2</FreeThrowsPercentage><OffensiveRebounds>9</OffensiveRebounds><DefensiveRebounds>24</DefensiveRebounds><Rebounds>33</Rebounds><OffensiveReboundsPercentage i:nil="true"/><DefensiveReboundsPercentage i:nil="true"/><TotalReboundsPercentage i:nil="true"/><Assists>17</Assists><Steals>9</Steals><BlockedShots>3</BlockedShots><Turnovers>10</Turnovers><PersonalFouls>20</PersonalFouls><Points>100</Points><TrueShootingAttempts>86.36</TrueShootingAttempts><TrueShootingPercentage>57.8</TrueShootingPercentage><PlayerEfficiencyRating i:nil="true"/><AssistsPercentage i:nil="true"/><StealsPercentage i:nil="true"/><BlocksPercentage i:nil="true"/><TurnOversPercentage i:nil="true"/><UsageRatePercentage i:nil="true"/><FantasyPointsFanDuel>179.10</FantasyPointsFanDuel><FantasyPointsDraftKings>189.75</FantasyPointsDraftKings><FantasyPointsYahoo>183.10</FantasyPointsYahoo></TeamGame><TeamGame><StatID>174546</StatID><TeamID>22</TeamID><SeasonType>1</SeasonType><Season>2015</Season><Name>Houston Rockets</Name><Team>HOU</Team><Wins>1</Wins><Losses>0</Losses><GameID>59</GameID><OpponentID>27</OpponentID><Opponent>LAL</Opponent><Day>10/28/2014</Day><DateTime>10/28/2014 10:30:00 PM</DateTime><HomeOrAway>AWAY</HomeOrAway><IsGameOver>True</IsGameOver><Updated>11/2/2015 11:55:33 PM</Updated><Games>1</Games><FantasyPoints>204.40</FantasyPoints><Minutes>240</Minutes><FieldGoalsMade>31</FieldGoalsMade><FieldGoalsAttempted>73</FieldGoalsAttempted><FieldGoalsPercentage>42.5</FieldGoalsPercentage><EffectiveFieldGoalsPercentage>50.7</EffectiveFieldGoalsPercentage><TwoPointersMade>19</TwoPointersMade><TwoPointersAttempted>44</TwoPointersAttempted><TwoPointersPercentage>43.2</TwoPointersPercentage><ThreePointersMade>12</ThreePointersMade><ThreePointersAttempted>29</ThreePointersAttempted><ThreePointersPercentage>41.4</ThreePointersPercentage><FreeThrowsMade>34</FreeThrowsMade><FreeThrowsAttempted>50</FreeThrowsAttempted><FreeThrowsPercentage>68.0</FreeThrowsPercentage><OffensiveRebounds>14</OffensiveRebounds><DefensiveRebounds>33</DefensiveRebounds><Rebounds>47</Rebounds><OffensiveReboundsPercentage i:nil="true"/><DefensiveReboundsPercentage i:nil="true"/><TotalReboundsPercentage i:nil="true"/><Assists>22</Assists><Steals>7</Steals><BlockedShots>3</BlockedShots><Turnovers>13</Turnovers><PersonalFouls>30</PersonalFouls><Points>108</Points><TrueShootingAttempts>95</TrueShootingAttempts><TrueShootingPercentage>56.8</TrueShootingPercentage><PlayerEfficiencyRating i:nil="true"/><AssistsPercentage i:nil="true"/><StealsPercentage i:nil="true"/><BlocksPercentage i:nil="true"/><TurnOversPercentage i:nil="true"/><UsageRatePercentage i:nil="true"/><FantasyPointsFanDuel>204.40</FantasyPointsFanDuel><FantasyPointsDraftKings>222.25</FantasyPointsDraftKings><FantasyPointsYahoo>210.40</FantasyPointsYahoo></TeamGame><TeamGame><StatID>174547</StatID><TeamID>27</TeamID><SeasonType>1</SeasonType><Season>2015</Season><Name>Los Angeles Lakers</Name><Team>LAL</Team><Wins>0</Wins><Losses>1</Losses><GameID>59</GameID><OpponentID>22</OpponentID><Opponent>HOU</Opponent><Day>10/28/2014</Day><DateTime>10/28/2014 10:30:00 PM</DateTime><HomeOrAway>HOME</HomeOrAway><IsGameOver>True</IsGameOver><Updated>11/2/2015 11:55:33 PM</Updated><Games>1</Games><FantasyPoints>166.20</FantasyPoints><Minutes>240</Minutes><FieldGoalsMade>28</FieldGoalsMade><FieldGoalsAttempted>79</FieldGoalsAttempted><FieldGoalsPercentage>35.4</FieldGoalsPercentage><EffectiveFieldGoalsPercentage>38.0</EffectiveFieldGoalsPercentage><TwoPointersMade>25</TwoPointersMade><TwoPointersAttempted>69</TwoPointersAttempted><TwoPointersPercentage>36.2</TwoPointersPercentage><ThreePointersMade>3</ThreePointersMade><ThreePointersAttempted>10</ThreePointersAttempted><ThreePointersPercentage>30.0</ThreePointersPercentage><FreeThrowsMade>31</FreeThrowsMade><FreeThrowsAttempted>39</FreeThrowsAttempted><FreeThrowsPercentage>79.5</FreeThrowsPercentage><OffensiveRebounds>11</OffensiveRebounds><DefensiveRebounds>25</DefensiveRebounds><Rebounds>36</Rebounds><OffensiveReboundsPercentage i:nil="true"/><DefensiveReboundsPercentage i:nil="true"/><TotalReboundsPercentage i:nil="true"/><Assists>16</Assists><Steals>7</Steals><BlockedShots>3</BlockedShots><Turnovers>11</Turnovers><PersonalFouls>32</PersonalFouls><Points>90</Points><TrueShootingAttempts>96.16</TrueShootingAttempts><TrueShootingPercentage>46.9</TrueShootingPercentage><PlayerEfficiencyRating i:nil="true"/><AssistsPercentage i:nil="true"/><StealsPercentage i:nil="true"/><BlocksPercentage i:nil="true"/><TurnOversPercentage i:nil="true"/><UsageRatePercentage i:nil="true"/><FantasyPointsFanDuel>166.20</FantasyPointsFanDuel><FantasyPointsDraftKings>175.00</FantasyPointsDraftKings><FantasyPointsYahoo>167.70</FantasyPointsYahoo></TeamGame><TeamGame><StatID>174556</StatID><TeamID>2</TeamID><SeasonType>1</SeasonType><Season>2015</Season><Name>Charlotte Hornets</Name><Team>CHA</Team><Wins>1</Wins><Losses>0</Losses><GameID>61</GameID><OpponentID>15</OpponentID><Opponent>MIL</Opponent><Day>10/29/2014</Day><DateTime>10/29/2014 7:00:00 PM</DateTime><HomeOrAway>HOME</HomeOrAway><IsGameOver>True</IsGameOver><Updated>11/2/2015 11:55:33 PM</Updated><Games>1</Games><FantasyPoints>232.50</FantasyPoints><Minutes>265</Minutes><FieldGoalsMade>41</FieldGoalsMade><FieldGoalsAttempted>101</FieldGoalsAttempted><FieldGoalsPercentage>40.6</FieldGoalsPercentage><EffectiveFieldGoalsPercentage>43.6</EffectiveFieldGoalsPercentage><TwoPointersMade>35</TwoPointersMade><TwoPointersAttempted>80</TwoPointersAttempted><TwoPointersPercentage>43.8</TwoPointersPercentage><ThreePointersMade>6</ThreePointersMade><ThreePointersAttempted>21</ThreePointersAttempted><ThreePointersPercentage>28.6</ThreePointersPercentage><FreeThrowsMade>20</FreeThrowsMade><FreeThrowsAttempted>29</FreeThrowsAttempted><FreeThrowsPercentage>69.0</FreeThrowsPercentage><OffensiveRebounds>15</OffensiveRebounds><DefensiveRebounds>35</DefensiveRebounds><Rebounds>50</Rebounds><OffensiveReboundsPercentage i:nil="true"/><DefensiveReboundsPercentage i:nil="true"/><TotalReboundsPercentage i:nil="true"/><Assists>27</Assists><Steals>8</Steals><BlockedShots>9</BlockedShots><Turnovers>10</Turnovers><PersonalFouls>20</PersonalFouls><Points>108</Points><TrueShootingAttempts>113.76</TrueShootingAttempts><TrueShootingPercentage>47.4</TrueShootingPercentage><PlayerEfficiencyRating i:nil="true"/><AssistsPercentage i:nil="true"/><StealsPercentage i:nil="true"/><BlocksPercentage i:nil="true"/><TurnOversPercentage i:nil="true"/><UsageRatePercentage i:nil="true"/><FantasyPointsFanDuel>232.50</FantasyPointsFanDuel><FantasyPointsDraftKings>244.50</FantasyPointsDraftKings><FantasyPointsYahoo>235.50</FantasyPointsYahoo></TeamGame><TeamGame><StatID>174557</StatID><TeamID>15</TeamID><SeasonType>1</SeasonType><Season>2015</Season><Name>Milwaukee Bucks</Name><Team>MIL</Team><Wins>0</Wins><Losses>1</Losses><GameID>61</GameID><OpponentID>2</OpponentID><Opponent>CHA</Opponent><Day>10/29/2014</Day><DateTime>10/29/2014 7:00:00 PM</DateTime><HomeOrAway>AWAY</HomeOrAway><IsGameOver>True</IsGameOver><Updated>11/2/2015 11:55:33 PM</Updated><Games>1</Games><FantasyPoints>209.50</FantasyPoints><Minutes>265</Minutes><FieldGoalsMade>39</FieldGoalsMade><FieldGoalsAttempted>80</FieldGoalsAttempted><FieldGoalsPercentage>48.8</FieldGoalsPercentage><EffectiveFieldGoalsPercentage>52.5</EffectiveFieldGoalsPercentage><TwoPointersMade>32</TwoPointersMade><TwoPointersAttempted>66</TwoPointersAttempted><TwoPointersPercentage>48.5</TwoPointersPercentage><ThreePointersMade>7</ThreePointersMade><ThreePointersAttempted>14</ThreePointersAttempted><ThreePointersPercentage>50.0</ThreePointersPercentage><FreeThrowsMade>21</FreeThrowsMade><FreeThrowsAttempted>24</FreeThrowsAttempted><FreeThrowsPercentage>87.5</FreeThrowsPercentage><OffensiveRebounds>3</OffensiveRebounds><DefensiveRebounds>32</DefensiveRebounds><Rebounds>35</Rebounds><OffensiveReboundsPercentage i:nil="true"/><DefensiveReboundsPercentage i:nil="true"/><TotalReboundsPercentage i:nil="true"/><Assists>25</Assists><Steals>9</Steals><BlockedShots>10</BlockedShots><Turnovers>14</Turnovers><PersonalFouls>25</PersonalFouls><Points>106</Points><TrueShootingAttempts>90.56</TrueShootingAttempts><TrueShootingPercentage>58.6</TrueShootingPercentage><PlayerEfficiencyRating i:nil="true"/><AssistsPercentage i:nil="true"/><StealsPercentage i:nil="true"/><BlocksPercentage i:nil="true"/><TurnOversPercentage i:nil="true"/><UsageRatePercentage i:nil="true"/><FantasyPointsFanDuel>209.50</FantasyPointsFanDuel><FantasyPointsDraftKings>223.25</FantasyPointsDraftKings><FantasyPointsYahoo>213.00</FantasyPointsYahoo></TeamGame><TeamGame><StatID>174562</StatID><TeamID>7</TeamID><SeasonType>1</SeasonType><Season>2015</Season><Name>Philadelphia 76ers</Name><Team>PHI</Team><Wins>0</Wins><Losses>1</Losses><GameID>60</GameID><OpponentID>13</OpponentID><Opponent>IND</Opponent><Day>10/29/2014</Day><DateTime>10/29/2014 7:00:00 PM</DateTime><HomeOrAway>AWAY</HomeOrAway><IsGameOver>True</IsGameOver><Updated>11/2/2015 11:55:33 PM</Updated><Games>1</Games><FantasyPoints>185.90</FantasyPoints><Minutes>240</Minutes><FieldGoalsMade>34</FieldGoalsMade><FieldGoalsAttempted>89</FieldGoalsAttempted><FieldGoalsPercentage>38.2</FieldGoalsPercentage><EffectiveFieldGoalsPercentage>41.6</EffectiveFieldGoalsPercentage><TwoPointersMade>28</TwoPointersMade><TwoPointersAttempted>68</TwoPointersAttempted><TwoPointersPercentage>41.2</TwoPointersPercentage><ThreePointersMade>6</ThreePointersMade><ThreePointersAttempted>21</ThreePointersAttempted><ThreePointersPercentage>28.6</ThreePointersPercentage><FreeThrowsMade>17</FreeThrowsMade><FreeThrowsAttempted>30</FreeThrowsAttempted><FreeThrowsPercentage>56.7</FreeThrowsPercentage><OffensiveRebounds>15</OffensiveRebounds><DefensiveRebounds>27</DefensiveRebounds><Rebounds>42</Rebounds><OffensiveReboundsPercentage i:nil="true"/><DefensiveReboundsPercentage i:nil="true"/><TotalReboundsPercentage i:nil="true"/><Assists>17</Assists><Steals>10</Steals><BlockedShots>5</BlockedShots><Turnovers>11</Turnovers><PersonalFouls>29</PersonalFouls><Points>91</Points><TrueShootingAttempts>102.2</TrueShootingAttempts><TrueShootingPercentage>44.6</TrueShootingPercentage><PlayerEfficiencyRating i:nil="true"/><AssistsPercentage i:nil="true"/><StealsPercentage i:nil="true"/><BlocksPercentage i:nil="true"/><TurnOversPercentage i:nil="true"/><UsageRatePercentage i:nil="true"/><FantasyPointsFanDuel>185.90</FantasyPointsFanDuel><FantasyPointsDraftKings>196.50</FantasyPointsDraftKings><FantasyPointsYahoo>188.90</FantasyPointsYahoo></TeamGame><TeamGame><StatID>174563</StatID><TeamID>13</TeamID><SeasonType>1</SeasonType><Season>2015</Season><Name>Indiana Pacers</Name><Team>IND</Team><Wins>1</Wins><Losses>0</Losses><GameID>60</GameID><OpponentID>7</OpponentID><Opponent>PHI</Opponent><Day>10/29/2014</Day><DateTime>10/29/2014 7:00:00 PM</DateTime><HomeOrAway>HOME</HomeOrAway><IsGameOver>True</IsGameOver><Updated>11/2/2015 11:55:33 PM</Updated><Games>1</Games><FantasyPoints>215.00</FantasyPoints><Minutes>240</Minutes><FieldGoalsMade>38</FieldGoalsMade><FieldGoalsAttempted>81</FieldGoalsAttempted><FieldGoalsPercentage>46.9</FieldGoalsPercentage><EffectiveFieldGoalsPercentage>51.9</EffectiveFieldGoalsPercentage><TwoPointersMade>30</TwoPointersMade><TwoPointersAttempted>56</TwoPointersAttempted><TwoPointersPercentage>53.6</TwoPointersPercentage><ThreePointersMade>8</ThreePointersMade><ThreePointersAttempted>25</ThreePointersAttempted><ThreePointersPercentage>32.0</ThreePointersPercentage><FreeThrowsMade>19</FreeThrowsMade><FreeThrowsAttempted>28</FreeThrowsAttempted><FreeThrowsPercentage>67.9</FreeThrowsPercentage><OffensiveRebounds>14</OffensiveRebounds><DefensiveRebounds>36</DefensiveRebounds><Rebounds>50</Rebounds><OffensiveReboundsPercentage i:nil="true"/><DefensiveReboundsPercentage i:nil="true"/><TotalReboundsPercentage i:nil="true"/><Assists>22</Assists><Steals>5</Steals><BlockedShots>13</BlockedShots><Turnovers>17</Turnovers><PersonalFouls>24</PersonalFouls><Points>103</Points><TrueShootingAttempts>93.32</TrueShootingAttempts><TrueShootingPercentage>55.1</TrueShootingPercentage><PlayerEfficiencyRating i:nil="true"/><AssistsPercentage i:nil="true"/><StealsPercentage i:nil="true"/><BlocksPercentage i:nil="true"/><TurnOversPercentage i:nil="true"/><UsageRatePercentage i:nil="true"/><FantasyPointsFanDuel>215.00</FantasyPointsFanDuel><FantasyPointsDraftKings>231.50</FantasyPointsDraftKings><FantasyPointsYahoo>219.00</FantasyPointsYahoo></TeamGame><TeamGame><StatID>174564</StatID><TeamID>1</TeamID><SeasonType>1</SeasonType><Season>2015</Season><Name>Washington Wizards</Name><Team>WAS</Team><Wins>0</Wins><Losses>1</Losses><GameID>63</GameID><OpponentID>4</OpponentID><Opponent>MIA</Opponent><Day>10/29/2014</Day><DateTime>10/29/2014 7:30:00 PM</DateTime><HomeOrAway>AWAY</HomeOrAway><IsGameOver>True</IsGameOver><Updated>11/2/2015 11:55:33 PM</Updated><Games>1</Games><FantasyPoints>172.20</FantasyPoints><Minutes>240</Minutes><FieldGoalsMade>36</FieldGoalsMade><FieldGoalsAttempted>75</FieldGoalsAttempted><FieldGoalsPercentage>48.0</FieldGoalsPercentage><EffectiveFieldGoalsPercentage>52.0</EffectiveFieldGoalsPercentage><TwoPointersMade>30</TwoPointersMade><TwoPointersAttempted>56</TwoPointersAttempted><TwoPointersPercentage>53.6</TwoPointersPercentage><ThreePointersMade>6</ThreePointersMade><ThreePointersAttempted>19</ThreePointersAttempted><ThreePointersPercentage>31.6</ThreePointersPercentage><FreeThrowsMade>17</FreeThrowsMade><FreeThrowsAttempted>24</FreeThrowsAttempted><FreeThrowsPercentage>70.8</FreeThrowsPercentage><OffensiveRebounds>7</OffensiveRebounds><DefensiveRebounds>29</DefensiveRebounds><Rebounds>36</Rebounds><OffensiveReboundsPercentage i:nil="true"/><DefensiveReboundsPercentage i:nil="true"/><TotalReboundsPercentage i:nil="true"/><Assists>20</Assists><Steals>7</Steals><BlockedShots>2</BlockedShots><Turnovers>14</Turnovers><PersonalFouls>20</PersonalFouls><Points>95</Points><TrueShootingAttempts>85.56</TrueShootingAttempts><TrueShootingPercentage>55.6</TrueShootingPercentage><PlayerEfficiencyRating i:nil="true"/><AssistsPercentage i:nil="true"/><StealsPercentage i:nil="true"/><BlocksPercentage i:nil="true"/><TurnOversPercentage i:nil="true"/><UsageRatePercentage i:nil="true"/><FantasyPointsFanDuel>172.20</FantasyPointsFanDuel><FantasyPointsDraftKings>185.50</FantasyPointsDraftKings><FantasyPointsYahoo>175.20</FantasyPointsYahoo></TeamGame><TeamGame><StatID>174565</StatID><TeamID>4</TeamID><SeasonType>1</SeasonType><Season>2015</Season><Name>Miami Heat</Name><Team>MIA</Team><Wins>1</Wins><Losses>0</Losses><GameID>63</GameID><OpponentID>1</OpponentID><Opponent>WAS</Opponent><Day>10/29/2014</Day><DateTime>10/29/2014 7:30:00 PM</DateTime><HomeOrAway>HOME</HomeOrAway><IsGameOver>True</IsGameOver><Updated>11/2/2015 11:55:33 PM</Updated><Games>1</Games><FantasyPoints>199.80</FantasyPoints><Minutes>240</Minutes><FieldGoalsMade>39</FieldGoalsMade><FieldGoalsAttempted>81</FieldGoalsAttempted><FieldGoalsPercentage>48.1</FieldGoalsPercentage><EffectiveFieldGoalsPercentage>54.3</EffectiveFieldGoalsPercentage><TwoPointersMade>30</TwoPointersMade><TwoPointersAttempted>53</TwoPointersAttempted><TwoPointersPercentage>56.6</TwoPointersPercentage><ThreePointersMade>9</ThreePointersMade><ThreePointersAttempted>28</ThreePointersAttempted><ThreePointersPercentage>32.1</ThreePointersPercentage><FreeThrowsMade>20</FreeThrowsMade><FreeThrowsAttempted>23</FreeThrowsAttempted><FreeThrowsPercentage>87.0</FreeThrowsPercentage><OffensiveRebounds>12</OffensiveRebounds><DefensiveRebounds>32</DefensiveRebounds><Rebounds>44</Rebounds><OffensiveReboundsPercentage i:nil="true"/><DefensiveReboundsPercentage i:nil="true"/><TotalReboundsPercentage i:nil="true"/><Assists>20</Assists><Steals>9</Steals><BlockedShots>3</BlockedShots><Turnovers>14</Turnovers><PersonalFouls>17</PersonalFouls><Points>107</Points><TrueShootingAttempts>91.12</TrueShootingAttempts><TrueShootingPercentage>58.8</TrueShootingPercentage><PlayerEfficiencyRating i:nil="true"/><AssistsPercentage i:nil="true"/><StealsPercentage i:nil="true"/><BlocksPercentage i:nil="true"/><TurnOversPercentage i:nil="true"/><UsageRatePercentage i:nil="true"/><FantasyPointsFanDuel>199.80</FantasyPointsFanDuel><FantasyPointsDraftKings>215.00</FantasyPointsDraftKings><FantasyPointsYahoo>204.30</FantasyPointsYahoo></TeamGame><TeamGame><StatID>174566</StatID><TeamID>3</TeamID><SeasonType>1</SeasonType><Season>2015</Season><Name>Atlanta Hawks</Name><Team>ATL</Team><Wins>0</Wins><Losses>1</Losses><GameID>64</GameID><OpponentID>10</OpponentID><Opponent>TOR</Opponent><Day>10/29/2014</Day><DateTime>10/29/2014 7:30:00 PM</DateTime><HomeOrAway>AWAY</HomeOrAway><IsGameOver>True</IsGameOver><Updated>11/2/2015 11:55:33 PM</Updated><Games>1</Games><FantasyPoints>202.40</FantasyPoints><Minutes>240</Minutes><FieldGoalsMade>40</FieldGoalsMade><FieldGoalsAttempted>80</FieldGoalsAttempted><FieldGoalsPercentage>50.0</FieldGoalsPercentage><EffectiveFieldGoalsPercentage>57.5</EffectiveFieldGoalsPercentage><TwoPointersMade>27</TwoPointersMade><TwoPointersAttempted>58</TwoPointersAttempted><TwoPointersPercentage>46.6</TwoPointersPercentage><ThreePointersMade>13</ThreePointersMade><ThreePointersAttempted>22</ThreePointersAttempted><ThreePointersPercentage>59.1</ThreePointersPercentage><FreeThrowsMade>9</FreeThrowsMade><FreeThrowsAttempted>17</FreeThrowsAttempted><FreeThrowsPercentage>52.9</FreeThrowsPercentage><OffensiveRebounds>10</OffensiveRebounds><DefensiveRebounds>32</DefensiveRebounds><Rebounds>42</Rebounds><OffensiveReboundsPercentage i:nil="true"/><DefensiveReboundsPercentage i:nil="true"/><TotalReboundsPercentage i:nil="true"/><Assists>26</Assists><Steals>6</Steals><BlockedShots>8</BlockedShots><Turnovers>17</Turnovers><PersonalFouls>24</PersonalFouls><Points>102</Points><TrueShootingAttempts>87.48</TrueShootingAttempts><TrueShootingPercentage>58.3</TrueShootingPercentage><PlayerEfficiencyRating i:nil="true"/><AssistsPercentage i:nil="true"/><StealsPercentage i:nil="true"/><BlocksPercentage i:nil="true"/><TurnOversPercentage i:nil="true"/><UsageRatePercentage i:nil="true"/><FantasyPointsFanDuel>202.40</FantasyPointsFanDuel><FantasyPointsDraftKings>222.50</FantasyPointsDraftKings><FantasyPointsYahoo>208.90</FantasyPointsYahoo></TeamGame><TeamGame><StatID>174567</StatID><TeamID>10</TeamID><SeasonType>1</SeasonType><Season>2015</Season><Name>Toronto Raptors</Name><Team>TOR</Team><Wins>1</Wins><Losses>0</Losses><GameID>64</GameID><OpponentID>3</OpponentID><Opponent>ATL</Opponent><Day>10/29/2014</Day><DateTime>10/29/2014 7:30:00 PM</DateTime><HomeOrAway>HOME</HomeOrAway><IsGameOver>True</IsGameOver><Updated>11/2/2015 11:55:33 PM</Updated><Games>1</Games><FantasyPoints>240.60</FantasyPoints><Minutes>240</Minutes><FieldGoalsMade>37</FieldGoalsMade><FieldGoalsAttempted>90</FieldGoalsAttempted><FieldGoalsPercentage>41.1</FieldGoalsPercentage><EffectiveFieldGoalsPercentage>45.6</EffectiveFieldGoalsPercentage><TwoPointersMade>29</TwoPointersMade><TwoPointersAttempted>64</TwoPointersAttempted><TwoPointersPercentage>45.3</TwoPointersPercentage><ThreePointersMade>8</ThreePointersMade><ThreePointersAttempted>26</ThreePointersAttempted><ThreePointersPercentage>30.8</ThreePointersPercentage><FreeThrowsMade>27</FreeThrowsMade><FreeThrowsAttempted>33</FreeThrowsAttempted><FreeThrowsPercentage>81.8</FreeThrowsPercentage><OffensiveRebounds>16</OffensiveRebounds><DefensiveRebounds>32</DefensiveRebounds><Rebounds>48</Rebounds><OffensiveReboundsPercentage i:nil="true"/><DefensiveReboundsPercentage i:nil="true"/><TotalReboundsPercentage i:nil="true"/><Assists>26</Assists><Steals>13</Steals><BlockedShots>9</BlockedShots><Turnovers>9</Turnovers><PersonalFouls>22</PersonalFouls><Points>109</Points><TrueShootingAttempts>104.52</TrueShootingAttempts><TrueShootingPercentage>52.2</TrueShootingPercentage><PlayerEfficiencyRating i:nil="true"/><AssistsPercentage i:nil="true"/><StealsPercentage i:nil="true"/><BlocksPercentage i:nil="true"/><TurnOversPercentage i:nil="true"/><UsageRatePercentage i:nil="true"/><FantasyPointsFanDuel>240.60</FantasyPointsFanDuel><FantasyPointsDraftKings>256.00</FantasyPointsDraftKings><FantasyPointsYahoo>244.60</FantasyPointsYahoo></TeamGame><TeamGame><StatID>174558</StatID><TeamID>8</TeamID><SeasonType>1</SeasonType><Season>2015</Season><Name>Brooklyn Nets</Name><Team>BKN</Team><Wins>0</Wins><Losses>1</Losses><GameID>62</GameID><OpponentID>9</OpponentID><Opponent>BOS</Opponent><Day>10/29/2014</Day><DateTime>10/29/2014 7:30:00 PM</DateTime><HomeOrAway>AWAY</HomeOrAway><IsGameOver>True</IsGameOver><Updated>11/2/2015 11:55:33 PM</Updated><Games>1</Games><FantasyPoints>187.80</FantasyPoints><Minutes>240</Minutes><FieldGoalsMade>39</FieldGoalsMade><FieldGoalsAttempted>80</FieldGoalsAttempted><FieldGoalsPercentage>48.8</FieldGoalsPercentage><EffectiveFieldGoalsPercentage>52.5</EffectiveFieldGoalsPercentage><TwoPointersMade>32</TwoPointersMade><TwoPointersAttempted>61</TwoPointersAttempted><TwoPointersPercentage>52.5</TwoPointersPercentage><ThreePointersMade>7</ThreePointersMade><ThreePointersAttempted>19</ThreePointersAttempted><ThreePointersPercentage>36.8</ThreePointersPercentage><FreeThrowsMade>20</FreeThrowsMade><FreeThrowsAttempted>26</FreeThrowsAttempted><FreeThrowsPercentage>76.9</FreeThrowsPercentage><OffensiveRebounds>9</OffensiveRebounds><DefensiveRebounds>30</DefensiveRebounds><Rebounds>39</Rebounds><OffensiveReboundsPercentage i:nil="true"/><DefensiveReboundsPercentage i:nil="true"/><TotalReboundsPercentage i:nil="true"/><Assists>20</Assists><Steals>6</Steals><BlockedShots>7</BlockedShots><Turnovers>20</Turnovers><PersonalFouls>21</PersonalFouls><Points>105</Points><TrueShootingAttempts>91.44</TrueShootingAttempts><TrueShootingPercentage>57.4</TrueShootingPercentage><PlayerEfficiencyRating i:nil="true"/><AssistsPercentage i:nil="true"/><StealsPercentage i:nil="true"/><BlocksPercentage i:nil="true"/><TurnOversPercentage i:nil="true"/><UsageRatePercentage i:nil="true"/><FantasyPointsFanDuel>187.80</FantasyPointsFanDuel><FantasyPointsDraftKings>203.25</FantasyPointsDraftKings><FantasyPointsYahoo>191.30</FantasyPointsYahoo></TeamGame><TeamGame><StatID>174559</StatID><TeamID>9</TeamID><SeasonType>1</SeasonType><Season>2015</Season><Name>Boston Celtics</Name><Team>BOS</Team><Wins>1</Wins><Losses>0</Losses><GameID>62</GameID><OpponentID>8</OpponentID><Opponent>BKN</Opponent><Day>10/29/2014</Day><DateTime>10/29/2014 7:30:00 PM</DateTime><HomeOrAway>HOME</HomeOrAway><IsGameOver>True</IsGameOver><Updated>11/2/2015 11:55:33 PM</Updated><Games>1</Games><FantasyPoints>225.00</FantasyPoints><Minutes>240</Minutes><FieldGoalsMade>49</FieldGoalsMade><FieldGoalsAttempted>88</FieldGoalsAttempted><FieldGoalsPercentage>55.7</FieldGoalsPercentage><EffectiveFieldGoalsPercentage>60.2</EffectiveFieldGoalsPercentage><TwoPointersMade>41</TwoPointersMade><TwoPointersAttempted>66</TwoPointersAttempted><TwoPointersPercentage>62.1</TwoPointersPercentage><ThreePointersMade>8</ThreePointersMade><ThreePointersAttempted>22</ThreePointersAttempted><ThreePointersPercentage>36.4</ThreePointersPercentage><FreeThrowsMade>15</FreeThrowsMade><FreeThrowsAttempted>23</FreeThrowsAttempted><FreeThrowsPercentage>65.2</FreeThrowsPercentage><OffensiveRebounds>9</OffensiveRebounds><DefensiveRebounds>26</DefensiveRebounds><Rebounds>35</Rebounds><OffensiveReboundsPercentage i:nil="true"/><DefensiveReboundsPercentage i:nil="true"/><TotalReboundsPercentage i:nil="true"/><Assists>28</Assists><Steals>11</Steals><BlockedShots>5</BlockedShots><Turnovers>12</Turnovers><PersonalFouls>25</PersonalFouls><Points>121</Points><TrueShootingAttempts>98.12</TrueShootingAttempts><TrueShootingPercentage>61.7</TrueShootingPercentage><PlayerEfficiencyRating i:nil="true"/><AssistsPercentage i:nil="true"/><StealsPercentage i:nil="true"/><BlocksPercentage i:nil="true"/><TurnOversPercentage i:nil="true"/><UsageRatePercentage i:nil="true"/><FantasyPointsFanDuel>225.00</FantasyPointsFanDuel><FantasyPointsDraftKings>238.25</FantasyPointsDraftKings><FantasyPointsYahoo>229.00</FantasyPointsYahoo></TeamGame><TeamGame><StatID>174560</StatID><TeamID>6</TeamID><SeasonType>1</SeasonType><Season>2015</Season><Name>New York Knicks</Name><Team>NY</Team><Wins i:nil="true"/><Losses i:nil="true"/><GameID>65</GameID><OpponentID>11</OpponentID><Opponent>CHI</Opponent><Day>10/29/2014</Day><DateTime>10/29/2014 8:00:00 PM</DateTime><HomeOrAway>HOME</HomeOrAway><IsGameOver>False</IsGameOver><Updated>11/2/2015 11:55:33 PM</Updated><Games>1</Games><FantasyPoints>171.10</FantasyPoints><Minutes>240</Minutes><FieldGoalsMade>31</FieldGoalsMade><FieldGoalsAttempted>85</FieldGoalsAttempted><FieldGoalsPercentage>36.5</FieldGoalsPercentage><EffectiveFieldGoalsPercentage>37.6</EffectiveFieldGoalsPercentage><TwoPointersMade>28</TwoPointersMade><TwoPointersAttempted>68</TwoPointersAttempted><TwoPointersPercentage>41.2</TwoPointersPercentage><ThreePointersMade>3</ThreePointersMade><ThreePointersAttempted>17</ThreePointersAttempted><ThreePointersPercentage>17.6</ThreePointersPercentage><FreeThrowsMade>15</FreeThrowsMade><FreeThrowsAttempted>17</FreeThrowsAttempted><FreeThrowsPercentage>88.2</FreeThrowsPercentage><OffensiveRebounds>14</OffensiveRebounds><DefensiveRebounds>24</DefensiveRebounds><Rebounds>38</Rebounds><OffensiveReboundsPercentage i:nil="true"/><DefensiveReboundsPercentage i:nil="true"/><TotalReboundsPercentage i:nil="true"/><Assists>19</Assists><Steals>9</Steals><BlockedShots>5</BlockedShots><Turnovers>11</Turnovers><PersonalFouls>22</PersonalFouls><Points>80</Points><TrueShootingAttempts>92.48</TrueShootingAttempts><TrueShootingPercentage>43.2</TrueShootingPercentage><PlayerEfficiencyRating i:nil="true"/><AssistsPercentage i:nil="true"/><StealsPercentage i:nil="true"/><BlocksPercentage i:nil="true"/><TurnOversPercentage i:nil="true"/><UsageRatePercentage i:nil="true"/><FantasyPointsFanDuel>171.10</FantasyPointsFanDuel><FantasyPointsDraftKings>180.00</FantasyPointsDraftKings><FantasyPointsYahoo>172.60</FantasyPointsYahoo></TeamGame><TeamGame><StatID>174561</StatID><TeamID>11</TeamID><SeasonType>1</SeasonType><Season>2015</Season><Name>Chicago Bulls</Name><Team>CHI</Team><Wins i:nil="true"/><Losses i:nil="true"/><GameID>65</GameID><OpponentID>6</OpponentID><Opponent>NY</Opponent><Day>10/29/2014</Day><DateTime>10/29/2014 8:00:00 PM</DateTime><HomeOrAway>AWAY</HomeOrAway><IsGameOver>False</IsGameOver><Updated>11/2/2015 11:55:33 PM</Updated><Games>1</Games><FantasyPoints>202.90</FantasyPoints><Minutes>240</Minutes><FieldGoalsMade>36</FieldGoalsMade><FieldGoalsAttempted>71</FieldGoalsAttempted><FieldGoalsPercentage>50.7</FieldGoalsPercentage><EffectiveFieldGoalsPercentage>56.3</EffectiveFieldGoalsPercentage><TwoPointersMade>29</TwoPointersMade><TwoPointersAttempted>47</TwoPointersAttempted><TwoPointersPercentage>61.7</TwoPointersPercentage><ThreePointersMade>7</ThreePointersMade><ThreePointersAttempted>24</ThreePointersAttempted><ThreePointersPercentage>29.2</ThreePointersPercentage><FreeThrowsMade>25</FreeThrowsMade><FreeThrowsAttempted>30</FreeThrowsAttempted><FreeThrowsPercentage>83.3</FreeThrowsPercentage><OffensiveRebounds>10</OffensiveRebounds><DefensiveRebounds>37</DefensiveRebounds><Rebounds>47</Rebounds><OffensiveReboundsPercentage i:nil="true"/><DefensiveReboundsPercentage i:nil="true"/><TotalReboundsPercentage i:nil="true"/><Assists>21</Assists><Steals>9</Steals><BlockedShots>4</BlockedShots><Turnovers>15</Turnovers><PersonalFouls>18</PersonalFouls><Points>104</Points><TrueShootingAttempts>84.2</TrueShootingAttempts><TrueShootingPercentage>61.9</TrueShootingPercentage><PlayerEfficiencyRating i:nil="true"/><AssistsPercentage i:nil="true"/><StealsPercentage i:nil="true"/><BlocksPercentage i:nil="true"/><TurnOversPercentage i:nil="true"/><UsageRatePercentage i:nil="true"/><FantasyPointsFanDuel>202.90</FantasyPointsFanDuel><FantasyPointsDraftKings>217.75</FantasyPointsDraftKings><FantasyPointsYahoo>206.40</FantasyPointsYahoo></TeamGame><TeamGame><StatID>174568</StatID><TeamID>16</TeamID><SeasonType>1</SeasonType><Season>2015</Season><Name>Minnesota Timberwolves</Name><Team>MIN</Team><Wins i:nil="true"/><Losses i:nil="true"/><GameID>66</GameID><OpponentID>21</OpponentID><Opponent>MEM</Opponent><Day>10/29/2014</Day><DateTime>10/29/2014 8:00:00 PM</DateTime><HomeOrAway>AWAY</HomeOrAway><IsGameOver>False</IsGameOver><Updated>11/2/2015 11:55:33 PM</Updated><Games>1</Games><FantasyPoints>188.40</FantasyPoints><Minutes>240</Minutes><FieldGoalsMade>39</FieldGoalsMade><FieldGoalsAttempted>86</FieldGoalsAttempted><FieldGoalsPercentage>45.3</FieldGoalsPercentage><EffectiveFieldGoalsPercentage>48.8</EffectiveFieldGoalsPercentage><TwoPointersMade>33</TwoPointersMade><TwoPointersAttempted>74</TwoPointersAttempted><TwoPointersPercentage>44.6</TwoPointersPercentage><ThreePointersMade>6</ThreePointersMade><ThreePointersAttempted>12</ThreePointersAttempted><ThreePointersPercentage>50.0</ThreePointersPercentage><FreeThrowsMade>17</FreeThrowsMade><FreeThrowsAttempted>23</FreeThrowsAttempted><FreeThrowsPercentage>73.9</FreeThrowsPercentage><OffensiveRebounds>19</OffensiveRebounds><DefensiveRebounds>28</DefensiveRebounds><Rebounds>47</Rebounds><OffensiveReboundsPercentage i:nil="true"/><DefensiveReboundsPercentage i:nil="true"/><TotalReboundsPercentage i:nil="true"/><Assists>20</Assists><Steals>8</Steals><BlockedShots>4</BlockedShots><Turnovers>23</Turnovers><PersonalFouls>21</PersonalFouls><Points>101</Points><TrueShootingAttempts>96.12</TrueShootingAttempts><TrueShootingPercentage>52.6</TrueShootingPercentage><PlayerEfficiencyRating i:nil="true"/><AssistsPercentage i:nil="true"/><StealsPercentage i:nil="true"/><BlocksPercentage i:nil="true"/><TurnOversPercentage i:nil="true"/><UsageRatePercentage i:nil="true"/><FantasyPointsFanDuel>188.40</FantasyPointsFanDuel><FantasyPointsDraftKings>205.25</FantasyPointsDraftKings><FantasyPointsYahoo>191.40</FantasyPointsYahoo></TeamGame><TeamGame><StatID>174569</StatID><TeamID>21</TeamID><SeasonType>1</SeasonType><Season>2015</Season><Name>Memphis Grizzlies</Name><Team>MEM</Team><Wins i:nil="true"/><Losses i:nil="true"/><GameID>66</GameID><OpponentID>16</OpponentID><Opponent>MIN</Opponent><Day>10/29/2014</Day><DateTime>10/29/2014 8:00:00 PM</DateTime><HomeOrAway>HOME</HomeOrAway><IsGameOver>False</IsGameOver><Updated>11/2/2015 11:55:33 PM</Updated><Games>1</Games><FantasyPoints>189.10</FantasyPoints><Minutes>240</Minutes><FieldGoalsMade>43</FieldGoalsMade><FieldGoalsAttempted>82</FieldGoalsAttempted><FieldGoalsPercentage>52.4</FieldGoalsPercentage><EffectiveFieldGoalsPercentage>54.9</EffectiveFieldGoalsPercentage><TwoPointersMade>39</TwoPointersMade><TwoPointersAttempted>67</TwoPointersAttempted><TwoPointersPercentage>58.2</TwoPointersPercentage><ThreePointersMade>4</ThreePointersMade><ThreePointersAttempted>15</ThreePointersAttempted><ThreePointersPercentage>26.7</ThreePointersPercentage><FreeThrowsMade>15</FreeThrowsMade><FreeThrowsAttempted>20</FreeThrowsAttempted><FreeThrowsPercentage>75.0</FreeThrowsPercentage><OffensiveRebounds>10</OffensiveRebounds><DefensiveRebounds>23</DefensiveRebounds><Rebounds>33</Rebounds><OffensiveReboundsPercentage i:nil="true"/><DefensiveReboundsPercentage i:nil="true"/><TotalReboundsPercentage i:nil="true"/><Assists>21</Assists><Steals>10</Steals><BlockedShots>5</BlockedShots><Turnovers>17</Turnovers><PersonalFouls>21</PersonalFouls><Points>105</Points><TrueShootingAttempts>90.8</TrueShootingAttempts><TrueShootingPercentage>57.7</TrueShootingPercentage><PlayerEfficiencyRating i:nil="true"/><AssistsPercentage i:nil="true"/><StealsPercentage i:nil="true"/><BlocksPercentage i:nil="true"/><TurnOversPercentage i:nil="true"/><UsageRatePercentage i:nil="true"/><FantasyPointsFanDuel>189.10</FantasyPointsFanDuel><FantasyPointsDraftKings>202.75</FantasyPointsDraftKings><FantasyPointsYahoo>191.10</FantasyPointsYahoo></TeamGame></ArrayOfTeamGame>